Topsis/__init__.py
Topsis/topsis.py
Topsis_SaiVarsha_102217040-1.0.1.dist-info/METADATA
Topsis_SaiVarsha_102217040-1.0.1.dist-info/WHEEL
Topsis_SaiVarsha_102217040-1.0.1.dist-info/entry_points.txt
Topsis_SaiVarsha_102217040-1.0.1.dist-info/top_level.txt
Topsis_SaiVarsha_102217040-1.0.1.dist-info/RECORD
