Metadata-Version: 2.1
Name: Topsis-SaiVarsha-102217040
Version: 1.0.1
Summary: A Python package to implement TOPSIS
Author: Varsha
Author-email: sgummadapu_be22@thapar.edu
Classifier: Programming Language :: Python :: 3
Classifier: License :: OSI Approved :: MIT License
Classifier: Operating System :: OS Independent
Requires-Python: >=3.6
Requires-Dist: pandas
Requires-Dist: numpy
